abvdev/__init__.py
abvdev/_client/attributes.py
abvdev/_client/client.py
abvdev/_client/constants.py
abvdev/_client/datasets.py
abvdev/_client/environment_variables.py
abvdev/_client/gateway.py
abvdev/_client/get_client.py
abvdev/_client/guardrails.py
abvdev/_client/observe.py
abvdev/_client/resource_manager.py
abvdev/_client/span.py
abvdev/_client/span_processor.py
abvdev/_client/utils.py
abvdev/_task_manager/media_manager.py
abvdev/_task_manager/media_upload_consumer.py
abvdev/_task_manager/media_upload_queue.py
abvdev/_task_manager/score_ingestion_consumer.py
abvdev/_utils/__init__.py
abvdev/_utils/environment.py
abvdev/_utils/error_logging.py
abvdev/_utils/parse_error.py
abvdev/_utils/prompt_cache.py
abvdev/_utils/request.py
abvdev/_utils/serializer.py
abvdev/api/README.md
abvdev/api/__init__.py
abvdev/api/client.py
abvdev/api/core/__init__.py
abvdev/api/core/api_error.py
abvdev/api/core/client_wrapper.py
abvdev/api/core/datetime_utils.py
abvdev/api/core/file.py
abvdev/api/core/http_client.py
abvdev/api/core/jsonable_encoder.py
abvdev/api/core/pydantic_utilities.py
abvdev/api/core/query_encoder.py
abvdev/api/core/remove_none_from_dict.py
abvdev/api/core/request_options.py
abvdev/api/reference.md
abvdev/api/resources/__init__.py
abvdev/api/resources/annotation_queues/__init__.py
abvdev/api/resources/annotation_queues/client.py
abvdev/api/resources/annotation_queues/types/__init__.py
abvdev/api/resources/annotation_queues/types/annotation_queue.py
abvdev/api/resources/annotation_queues/types/annotation_queue_assignment_request.py
abvdev/api/resources/annotation_queues/types/annotation_queue_item.py
abvdev/api/resources/annotation_queues/types/annotation_queue_object_type.py
abvdev/api/resources/annotation_queues/types/annotation_queue_status.py
abvdev/api/resources/annotation_queues/types/create_annotation_queue_assignment_response.py
abvdev/api/resources/annotation_queues/types/create_annotation_queue_item_request.py
abvdev-0.0.1b7.dist-info/METADATA
abvdev-0.0.1b7.dist-info/WHEEL
abvdev-0.0.1b7.dist-info/entry_points.txt
abvdev-0.0.1b7.dist-info/RECORD
